{
    "variants": {
      "": [
        {"model": "block/brown_mushroom/0" , "distance":1},
        {"model": "block/brown_mushroom/0" , "distance":1 ,"y":90},
        {"model": "block/brown_mushroom/0" , "distance":1 ,"y":180},
        {"model": "block/brown_mushroom/0" , "distance":1 ,"y":270},
        {"model": "block/brown_mushroom/1" , "distance":1},
        {"model": "block/brown_mushroom/1" , "distance":1 ,"y":90},
        {"model": "block/brown_mushroom/1" , "distance":1 ,"y":180},
        {"model": "block/brown_mushroom/1" , "distance":1 ,"y":270},
        {"model": "block/brown_mushroom/2" , "distance":1},
        {"model": "block/brown_mushroom/2" , "distance":1 ,"y":90},
        {"model": "block/brown_mushroom/2" , "distance":1 ,"y":180},
        {"model": "block/brown_mushroom/2" , "distance":1 ,"y":270}
      ]
    }
  }